{
  "stages": [
    { "id": "TutorialStage", "name": "教程庭院", "rtid": "RTID(TutorialStage@LevelModules)", "type": "main", "image": "Stage_Modern.webp" },
    { "id": "EgyptStage", "name": "神秘埃及", "rtid": "RTID(EgyptStage@LevelModules)", "type": "main", "image": "Stage_Egypt.webp" },
    { "id": "PirateStage", "name": "海盗港湾", "rtid": "RTID(PirateStage@LevelModules)", "type": "main", "image": "Stage_Pirate.webp" },
    { "id": "WestStage", "name": "狂野西部", "rtid": "RTID(WestStage@LevelModules)", "type": "main", "image": "Stage_West.webp" },
    { "id": "KongfuStage", "name": "功夫世界", "rtid": "RTID(KongfuStage@LevelModules)", "type": "main", "image": "Stage_Kongfu.webp" },
    { "id": "FutureStage", "name": "遥远未来", "rtid": "RTID(FutureStage@LevelModules)", "type": "main", "image": "Stage_Future.webp" },
    { "id": "DarkStage", "name": "黑暗时代", "rtid": "RTID(DarkStage@LevelModules)", "type": "main", "image": "Stage_Dark.webp" },
    { "id": "BeachStage", "name": "巨浪沙滩", "rtid": "RTID(BeachStage@LevelModules)", "type": "main", "image": "Stage_Beach.webp" },
    { "id": "IceageStage", "name": "冰河世纪", "rtid": "RTID(IceageStage@LevelModules)", "type": "main", "image": "Stage_Iceage.webp" },
    { "id": "LostCityStage", "name": "失落之城", "rtid": "RTID(LostCityStage@LevelModules)", "type": "main", "image": "Stage_LostCity.webp" },
    { "id": "SkycityStage", "name": "天空之城", "rtid": "RTID(SkycityStage@LevelModules)", "type": "main", "image": "Stage_Skycity.webp" },
    { "id": "EightiesStage", "name": "摇滚年代", "rtid": "RTID(EightiesStage@LevelModules)", "type": "main", "image": "Stage_Eighties.webp" },
    { "id": "DinoStage", "name": "恐龙危机", "rtid": "RTID(DinoStage@LevelModules)", "type": "main", "image": "Stage_Dino.webp" },
    { "id": "ModernStage", "name": "现代世界", "rtid": "RTID(ModernStage@LevelModules)", "type": "main", "image": "Stage_Modern.webp" },
    { "id": "SteamStage", "name": "蒸汽时代", "rtid": "RTID(SteamStage@LevelModules)", "type": "main", "image": "Stage_Steam.webp" },
    { "id": "RenaiStage", "name": "复兴时代", "rtid": "RTID(RenaiStage@LevelModules)", "type": "main", "image": "Stage_Renai.webp" },
    { "id": "HeianStage", "name": "平安时代", "rtid": "RTID(HeianStage@LevelModules)", "type": "main", "image": "Stage_Heian.webp" },
    { "id": "DeepseaStage", "name": "深海地图", "rtid": "RTID(DeepseaStage@LevelModules)", "type": "main", "image": "Stage_Atlantis.webp" },
    { "id": "DeepseaLandStage", "name": "亚特兰蒂斯", "rtid": "RTID(DeepseaLandStage@LevelModules)", "type": "main", "image": "Stage_Atlantis.webp" },

    { "id": "FairyTaleStage", "name": "童话森林", "rtid": "RTID(FairyTaleStage@LevelModules)", "type": "extra", "image": null },
    { "id": "ZCorpStage", "name": "Z公司", "rtid": "RTID(ZCorpStage@LevelModules)", "type": "extra", "image": null },
    { "id": "FrontLawnSpringStage", "name": "复活节", "rtid": "RTID(FrontLawnSpringStage@LevelModules)", "type": "extra", "image": null },
    { "id": "ChildrenDayStage", "name": "儿童节", "rtid": "RTID(ChildrenDayStage@LevelModules)", "type": "extra", "image": null },
    { "id": "HalloweenStage", "name": "万圣节", "rtid": "RTID(HalloweenStage@LevelModules)", "type": "extra", "image": null },
    { "id": "UnchartedAnniversaryStage", "name": "周年庆", "rtid": "RTID(UnchartedAnniversaryStage@LevelModules)", "type": "extra", "image": null },
    { "id": "VacationLostCityStage", "name": "失落火山", "rtid": "RTID(VacationLostCityStage@LevelModules)", "type": "extra", "image": null },
    { "id": "UnchartedIceageStage", "name": "冰河再临", "rtid": "RTID(UnchartedIceageStage@LevelModules)", "type": "extra", "image": null },
    { "id": "RunningNormalStage", "name": "地铁酷跑联动", "rtid": "RTID(RunningNormalStage@LevelModules)", "type": "extra", "image": null },
    { "id": "UnchartedNeedforspeedStage", "name": "极品飞车联动", "rtid": "RTID(UnchartedNeedforspeedStage@LevelModules)", "type": "extra", "image": null },
    { "id": "UnchartedNo42UniverseStage", "name": "平行宇宙秘境", "rtid": "RTID(UnchartedNo42UniverseStage@LevelModules)", "type": "extra", "image": null },
    { "id": "JourneyToTheWestStage", "name": "西游地图", "rtid": "RTID(JourneyToTheWestStage@LevelModules)", "type": "extra", "image": null },
    { "id": "UnchartedMausoleumStage", "name": "地宫地图", "rtid": "RTID(UnchartedMausoleumStage@LevelModules)", "type": "extra", "image": null },
    { "id": "RiftStage", "name": "潘妮的追击", "rtid": "RTID(RiftStage@LevelModules)", "type": "extra", "image": null },
    { "id": "JoustStage", "name": "超Z联赛", "rtid": "RTID(JoustStage@LevelModules)", "type": "extra", "image": null },

    { "id": "TwisterStage", "name": "前院白天", "rtid": "RTID(TwisterStage@LevelModules)", "type": "seasons", "image": null },
    { "id": "NightStage", "name": "前院夜晚", "rtid": "RTID(NightStage@LevelModules)", "type": "seasons", "image": null },
    { "id": "PoolDaylightStage", "name": "泳池白天", "rtid": "RTID(PoolDaylightStage@LevelModules)", "type": "seasons", "image": null },
    { "id": "PoolNightStage", "name": "泳池夜晚", "rtid": "RTID(PoolNightStage@LevelModules)", "type": "seasons", "image": null },
    { "id": "RoofStage", "name": "屋顶白天", "rtid": "RTID(RoofStage@LevelModules)", "type": "seasons", "image": null },
    { "id": "RoofNightStage", "name": "屋顶夜晚", "rtid": "RTID(RoofNightStage@LevelModules)", "type": "seasons", "image": null },
    { "id": "NewYearDaylightStage", "name": "新春白天", "rtid": "RTID(NewYearDaylightStage@LevelModules)", "type": "seasons", "image": null },
    { "id": "NewYearNightStage", "name": "新春黑夜", "rtid": "RTID(NewYearNightStage@LevelModules)", "type": "seasons", "image": null },
    { "id": "SpringDaylightStage", "name": "春日白天", "rtid": "RTID(SpringDaylightStage@LevelModules)", "type": "seasons", "image": null },
    { "id": "SpringNightStage", "name": "春日夜晚", "rtid": "RTID(SpringNightStage@LevelModules)", "type": "seasons", "image": null },
    { "id": "SummerDaylightStage", "name": "仲夏白天", "rtid": "RTID(SummerDaylightStage@LevelModules)", "type": "seasons", "image": null },
    { "id": "SummerNightStage", "name": "仲夏夜晚", "rtid": "RTID(SummerNightStage@LevelModules)", "type": "seasons", "image": null },
    { "id": "AutumnEarlyStage", "name": "秋季初秋", "rtid": "RTID(AutumnEarlyStage@LevelModules)", "type": "seasons", "image": null },
    { "id": "AutumnLateStage", "name": "秋季晚秋", "rtid": "RTID(AutumnLateStage@LevelModules)", "type": "seasons", "image": null },
    { "id": "SnowModernStage", "name": "冬日白天", "rtid": "RTID(SnowModernStage@LevelModules)", "type": "seasons", "image": null },
    { "id": "SnowNightStage", "name": "冬日夜晚", "rtid": "RTID(SnowNightStage@LevelModules)", "type": "seasons", "image": null },
    { "id": "SnowRoofStage", "name": "冬日屋顶", "rtid": "RTID(SnowRoofStage@LevelModules)", "type": "seasons", "image": null },
    { "id": "UnchartedArbordayStage", "name": "踏雪寻春", "rtid": "RTID(UnchartedArbordayStage@LevelModules)", "type": "seasons", "image": null },

    { "id": "TheatreDarkStage", "name": "黑暗剧院", "rtid": "RTID(TheatreDarkStage@LevelModules)", "type": "special", "image": null },
    { "id": "BeachSnakeStage", "name": "鳄梨贪吃蛇", "rtid": "RTID(BeachSnakeStage@LevelModules)", "type": "special", "image": null },
    { "id": "IceageRiverCrossingStage", "name": "渡渡鸟历险", "rtid": "RTID(IceageRiverCrossingStage@LevelModules)", "type": "special", "image": null },
    { "id": "IceageEliminateStage", "name": "冰河连连看", "rtid": "RTID(IceageEliminateStage@LevelModules)", "type": "special", "image": null },
    { "id": "SkycityFishingStage", "name": "一炮当关", "rtid": "RTID(SkycityFishingStage@LevelModules)", "type": "special", "image": null },
    { "id": "SkycityPooyanStage", "name": "壮植凌云", "rtid": "RTID(SkycityPooyanStage@LevelModules)", "type": "special", "image": null },
    { "id": "AquariumStage", "name": "水族馆", "rtid": "RTID(AquariumStage@LevelModules)", "type": "special", "image": null },
    { "id": "BowlingStage", "name": "保龄球", "rtid": "RTID(BowlingStage@LevelModules)", "type": "special", "image": null },
    { "id": "WhackAMoleStage", "name": "锤僵尸", "rtid": "RTID(WhackAMoleStage@LevelModules)", "type": "special", "image": null },
    { "id": "CardGameStage", "name": "牌面纷争", "rtid": "RTID(CardGameStage@LevelModules)", "type": "special", "image": null },
    { "id": "OverwhelmStage", "name": "排山倒海", "rtid": "RTID(OverwhelmStage@LevelModules)", "type": "special", "image": null },
    { "id": "OverwhelmSnowModernStage", "name": "冬日排山倒海", "rtid": "RTID(OverwhelmSnowModernStage@LevelModules)", "type": "special", "image": null },
    { "id": "OverwhelmSnowRoofStage", "name": "冬日排山倒海屋顶", "rtid": "RTID(OverwhelmSnowRoofStage@LevelModules)", "type": "special", "image": null },
    { "id": "OverwhelmSnowNightStage", "name": "冬日排山倒海夜晚", "rtid": "RTID(OverwhelmSnowNightStage@LevelModules)", "type": "special", "image": null }
  ]
}
